{"version":"v2.0.0","name":"BRYMBO-PENTRE-BROUGHTON-SCHOOL","gauges":[{"name":"BRYMBO-PENTRE-BROUGHTON-SCHOOL","ranges":[["1915/11","1915/11"],["1916/01","1916/02"],["1916/04","1916/05"],["1919/01","1919/01"],["1919/04","1924/12"],["1926/01","1931/01"],["1931/03","1931/03"],["1931/05","1933/07"],["1933/09","1934/12"]]}],"links":{"folder":"https://github.com/ed-hawkins/rainfall-rescue/tree/v2.0.0/DATA/BRYMBO-PENTRE-BROUGHTON-SCHOOL"},"history":[{"version":"v2.0.0","location":"BRYMBO-PENTRE-BROUGHTON-SCHOOL","changes":["New"]}]}