{"version":"v2.0.0","name":"FESTINIOG-BLAENYDDOL","gauges":[{"name":"FESTINIOG-BLAENYDDOL","ranges":[["1864/06","1873/02"]]}],"links":{"folder":"https://github.com/ed-hawkins/rainfall-rescue/tree/v2.0.0/DATA/FESTINIOG-BLAENYDDOL"},"history":[{"version":"v1.0.0","location":"FESTINIOG-BLAENYDDOL","changes":["New"]},{"version":"v1.1.0","location":"FESTINIOG-BLAENYDDOL","changes":[]},{"version":"v2.0.0","location":"FESTINIOG-BLAENYDDOL","changes":[]},{"version":"working","location":"FESTINIOG-BLAENYDDOL","changes":[]}]}