{"version":"v1.0.0","name":"BALA-CRAIG-NANT","gauges":[{"name":"BALA-CRAIG-NANT","ranges":[["1939/01","1941/11"],["1942/01","1943/12"],["1944/02","1944/12"],["1945/02","1945/07"],["1945/09","1946/09"],["1946/12","1951/12"],["1952/02","1952/05"],["1952/07","1952/12"],["1953/04","1953/05"],["1953/07","1953/09"],["1953/11","1954/12"],["1957/04","1957/05"],["1958/03","1958/05"],["1958/07","1958/08"],["1958/10","1960/11"]]}],"links":{"folder":"https://github.com/ed-hawkins/rainfall-rescue/tree/v1.0.0/DATA/BALA-CRAIG-NANT"},"history":[{"version":"v1.0.0","location":"BALA-CRAIG-NANT","changes":["New"]},{"version":"v1.1.0","location":"BALA-CRAIG-NANT","changes":[]},{"version":"working","location":"BALA-CRAIG-NANT","changes":[]}]}