{"version":"v1.0.0","name":"COWES-STEPHENSON-ROAD","gauges":[{"name":"COWES-STEPHENSON-ROAD","ranges":[["1891/01","1902/12"]]},{"name":"COWES-STEPHENSON-ROAD-2","ranges":[["1902/01","1905/12"]]},{"name":"COWES-STEPHENSON-ROAD-3","ranges":[["1906/01","1912/03"]]},{"name":"COWES-STEPHENSON-ROAD-4","ranges":[["1912/05","1924/12"]]}],"links":{"TYRSheets":"https://github.com/ed-hawkins/rainfall-rescue/blob/v1.0.0/DATA/COWES-STEPHENSON-ROAD/COWES-STEPHENSON-ROAD.pdf"},"history":[{"version":"v1.0.0","name":"COWES-STEPHENSON-ROAD","changes":["New"]}]}