{"version":"v1.0.0","name":"CRESSAGE-HARNAGE-GRANGE","gauges":[{"name":"CRESSAGE-HARNAGE-GRANGE","ranges":[["1934/06","1959/01"],["1959/03","1959/08"],["1959/10","1959/12"]]}],"links":{"folder":"https://github.com/ed-hawkins/rainfall-rescue/tree/v1.0.0/DATA/CRESSAGE-HARNAGE-GRANGE"},"history":[{"version":"v1.0.0","location":"CRESSAGE-HARNAGE-GRANGE","changes":["New"]},{"version":"v1.1.0","location":"CRESSAGE-HARNAGE-GRANGE","changes":[]},{"version":"v2.0.0","location":"CRESSAGE-HARNAGE-GRANGE","changes":[]},{"version":"working","location":"CRESSAGE-HARNAGE-GRANGE","changes":[]}]}