{"version":"v1.0.0","name":"DERBY-DUFFIELD","gauges":[{"name":"DERBY-DUFFIELD","ranges":[["1866/09","1889/12"]]},{"name":"DERBY-DUFFIELD-2","ranges":[["1895/07","1909/10"],["1910/01","1916/12"]]},{"name":"DERBY-DUFFIELD-3","ranges":[["1905/01","1909/10"]]}],"links":{"folder":"https://github.com/ed-hawkins/rainfall-rescue/tree/v1.0.0/DATA/DERBY-DUFFIELD"},"history":[{"version":"v1.0.0","location":"DERBY-DUFFIELD","changes":["New"]},{"version":"v1.1.0","location":"DERBY-DUFFIELD","changes":[]},{"version":"v2.0.0","location":"DERBY-DUFFIELD","changes":[]}]}