{"version":"v1.0.0","name":"EDINBURGH-CHARLOTTE-SQUARE","gauges":[{"name":"EDINBURGH-CHARLOTTE-SQUARE","ranges":[["1847/01","1852/12"],["1853/05","1860/08"],["1860/10","1861/08"],["1862/01","1862/09"],["1862/12","1862/12"],["1863/03","1870/09"],["1870/11","1896/12"],["1898/01","1909/12"],["1920/01","1923/12"]]},{"name":"EDINBURGH-CHARLOTTE-SQUARE-2","ranges":[["1850/01","1862/09"],["1862/12","1862/12"],["1863/03","1909/12"],["1920/01","1920/04"],["1920/06","1923/12"]]}],"links":{"folder":"https://github.com/ed-hawkins/rainfall-rescue/tree/v1.0.0/DATA/EDINBURGH-CHARLOTTE-SQUARE"},"history":[{"version":"v1.0.0","name":"EDINBURGH-CHARLOTTE-SQUARE","changes":["New"]}]}