{"version":"v1.0.0","name":"HENLEY-ON-THAMES-GREYS-GREEN","gauges":[{"name":"HENLEY-ON-THAMES-GREYS-GREEN","ranges":[["1871/06","1916/12"],["1918/08","1941/12"]]}],"links":{"folder":"https://github.com/ed-hawkins/rainfall-rescue/tree/v1.0.0/DATA/HENLEY-ON-THAMES-GREYS-GREEN"},"history":[{"version":"v1.0.0","location":"HENLEY-ON-THAMES-GREYS-GREEN","changes":["New"]},{"version":"v1.1.0","location":"HENLEY-ON-THAMES-GREYS-GREEN","changes":[]},{"version":"v2.0.0","location":"HENLEY-ON-THAMES-GREYS-GREEN","changes":[]}]}