{"version":"v1.0.0","name":"LANGSETT-MOOR-BORDER-HILL","gauges":[{"name":"LANGSETT-MOOR-BORDER-HILL","ranges":[["1910/01","1940/12"],["1941/03","1942/01"],["1942/04","1960/12"]]}],"links":{"folder":"https://github.com/ed-hawkins/rainfall-rescue/tree/v1.0.0/DATA/LANGSETT-MOOR-BORDER-HILL"},"history":[{"version":"v1.0.0","location":"LANGSETT-MOOR-BORDER-HILL","changes":["New"]},{"version":"v1.1.0","location":"LANGSETT-MOOR-BORDER-HILL","changes":[]},{"version":"working","location":"LANGSETT-MOOR-BORDER-HILL","changes":[]}]}