{"version":"v1.0.0","name":"LOCH-QUOICH-LOAN","gauges":[{"name":"LOCH-QUOICH-LOAN","ranges":[["1908/10","1929/07"],["1929/12","1931/08"],["1931/11","1933/11"],["1934/01","1934/02"],["1934/04","1934/04"],["1934/11","1939/08"],["1939/10","1939/12"],["1940/11","1941/02"],["1943/07","1944/12"],["1945/02","1945/04"],["1945/11","1946/03"],["1947/01","1947/02"],["1947/04","1947/04"],["1954/01","1955/08"]]}],"links":{"folder":"https://github.com/ed-hawkins/rainfall-rescue/tree/v1.0.0/DATA/LOCH-QUOICH-LOAN"},"history":[{"version":"v1.0.0","location":"LOCH-QUOICH-LOAN","changes":["New"]},{"version":"v1.1.0","location":"LOCH-QUOICH-LOAN","changes":[]},{"version":"v2.0.0","location":"LOCH-QUOICH-LOAN","changes":[]},{"version":"working","location":"LOCH-QUOICH-LOAN","changes":[]}]}