{"version":"v1.0.0","name":"WEDNESBURY-OCKER-HILL","gauges":[{"name":"WEDNESBURY-OCKER-HILL","ranges":[["1897/01","1949/06"],["1949/10","1953/12"],["1955/01","1959/12"]]}],"links":{"folder":"https://github.com/ed-hawkins/rainfall-rescue/tree/v1.0.0/DATA/WEDNESBURY-OCKER-HILL"},"history":[{"version":"v1.0.0","location":"WEDNESBURY-OCKER-HILL","changes":["New"]},{"version":"v1.1.0","location":"WEDNESBURY-OCKER-HILL","changes":[]},{"version":"v2.0.0","location":"WEDNESBURY-OCKER-HILL","changes":[]},{"version":"working","location":"WEDNESBURY-OCKER-HILL","changes":[]}]}