{"version":"working","name":"ABERDEEN-HUNTLY-LODGE","location":"ABERDEEN-HUNTLY-LODGE","metadata":{"station":"HUNTLY LODGE, ABERDEEN","gridRef":"NJ532413","stationNo":"RR6565","lon":-2.78168,"lat":57.45956,"elevation":425,"counties":["Aberdeenshire"]},"table":[[1820,1821,1822,1823,1824,1825,1826,1827,1828,1829],["","","","","","","","","",""],["","","","","","","","","",""],["","","","","","","","","",""],["","","","","","","","","",""],["","","","","","","","","",""],["","","","","","","","","",""],["","","","","","","","","",""],["","","","","","","","","",""],["","","","","","","","","",""],["","","","","","","","","",""],["","","","","","","","","",""],["","","","","","","","","",""],["","25","24.03","27.8","28.31","24.01","20.32","30.24","23.94","30.96"]],"structure":{"data":[{"startDate":"1820/01","endDate":"1821/08","filename":"TYRain_1820-1829_C_pt2-page-030.jpg"},{"startDate":"1821/10","endDate":"1821/10","filename":"TYRain_1820-1829_C_pt2-page-030.jpg"},{"startDate":"1821/12","endDate":"1822/06","filename":"TYRain_1820-1829_C_pt2-page-030.jpg"},{"startDate":"1822/08","endDate":"1823/08","filename":"TYRain_1820-1829_C_pt2-page-030.jpg"},{"startDate":"1823/11","endDate":"1824/08","filename":"TYRain_1820-1829_C_pt2-page-030.jpg"},{"startDate":"1824/11","endDate":"1825/07","filename":"TYRain_1820-1829_C_pt2-page-030.jpg"},{"startDate":"1825/09","endDate":"1826/10","filename":"TYRain_1820-1829_C_pt2-page-030.jpg"},{"startDate":"1826/12","endDate":"1827/08","filename":"TYRain_1820-1829_C_pt2-page-030.jpg"},{"startDate":"1827/11","endDate":"1828/07","filename":"TYRain_1820-1829_C_pt2-page-030.jpg"},{"startDate":"1828/09","endDate":"1828/09","filename":"TYRain_1820-1829_C_pt2-page-030.jpg"},{"startDate":"1828/11","endDate":"1829/06","filename":"TYRain_1820-1829_C_pt2-page-030.jpg"},{"startDate":"1829/12","endDate":"1829/13","filename":"TYRain_1820-1829_C_pt2-page-030.jpg"}],"external":[]},"comments":["sparse data for all years removed and into second csv without totals"],"links":{"dataFile":"https://raw.githubusercontent.com/ed-hawkins/rainfall-rescue-data-v2/main/DATA/ABERDEEN-HUNTLY-LODGE/ABERDEEN-HUNTLY-LODGE.csv"},"history":[{"version":"working","location":"ABERDEEN-HUNTLY-LODGE","name":"ABERDEEN-HUNTLY-LODGE","changes":["New"]}]}