{"version":"working","name":"CATCOTT-SHALLARDS","location":"CATCOTT-SHALLARDS","metadata":{"station":"CATCOTT-SHALLARDS","gridRef":"ST392393","stationNo":"2006/9/8","lon":-2.87063,"lat":51.1497,"elevation":140,"counties":["Somerset"]},"table":[[1951,1952,1953,1954,1955,1956,1957,1958,1959,1960],["","","","","","","","","","3.25"],["","","","","","","","","","2.48"],["","","","","","","","","","1.68"],["","","","","","","","","","2.14"],["","","","","","","","","","1.17"],["","","","","","","","","","1.87"],["","","","","","","","","","5.08"],["","","","","","","","","","3.45"],["","","","","","","","","","3.7"],["","","","","","","","","","8.06"],["","","","","","","","","","2.99"],["","","","","","","","","","2.89"],["","","","","","","","","","38.76"]],"structure":{"data":[{"startDate":"1951/01","endDate":"1960/13","filename":"TYRain_1951-1960_12_pt1-page-015.jpg"}],"external":[]},"comments":["House not found NGR taken from MIDAS","Post 1960 known as Catcott SRC_ID 9306","1960-1966"],"links":{"dataFile":"https://raw.githubusercontent.com/ed-hawkins/rainfall-rescue-data-v3/main/DATA/CATCOTT-SHALLARDS/CATCOTT-SHALLARDS.csv"},"history":[{"version":"working","location":"CATCOTT-SHALLARDS","name":"CATCOTT-SHALLARDS","changes":["New"]}]}