{"version":"working","name":"CROUCH-END-FAIRFIELD-ROAD","location":"CROUCH-END-FAIRFIELD-ROAD","metadata":{"station":"CROUCH-END-FAIRFIELD-ROAD-GARDEN","gridRef":"TQ303885","stationNo":"RR6182","lon":-0.12089,"lat":51.58031,"elevation":144,"counties":["Middlesex"]},"table":[[1890,1891,1892,1893,1894,1895,1896,1897,1898,1899],["","","","","","2.04","0.86","2.13","0.72","2.65"],["","","","","","0.12","0.34","3","1.17","2.17"],["","","","","","1.59","3.6","3.62","1.48","0.58"],["","","","","","1.25","0.56","2.02","1.27","2.85"],["","","","","","0.46","0.22","1.62","2.35","1.47"],["","","","","","0.48","1.75","2.6","1.18","1.65"],["","","","","","3.8","1.19","2.49","0.99","1.73"],["","","","","","3.33","1.73","2.86","1.46","0.57"],["","","","","","1.16","6.18","2.77","0.39","3.06"],["","","","","","2.84","3.26","0.66","3.32","2.33"],["","","","","","3.73","1.16","1.04","2.02","4.21"],["","","","","","2.34","3.94","2.49","2.51","1.03"],["","","","","","23.14","24.79","27.3","18.86","24.3"]],"structure":{"data":[{"startDate":"1890/01","endDate":"1899/13","filename":"TYRain_1890-1899_01_pt1-page-136.jpg"}],"external":[]},"comments":["NGR is mid-point of Fairfield Road.","Stated altitude is a few feet high.","NGR could be +/- 100m.","640m from CROUCH-END-PRIORY-PARK"],"links":{"dataFile":"https://raw.githubusercontent.com/ed-hawkins/rainfall-rescue/working/DATA/CROUCH-END-FAIRFIELD-ROAD/CROUCH-END-FAIRFIELD-ROAD.csv"},"history":[{"version":"working","name":"CROUCH-END-FAIRFIELD-ROAD","location":"CROUCH-END-FAIRFIELD-ROAD","changes":["New"]}]}