{"version":"working","name":"DUMFRIES-KELTON-HOUSE","location":"DUMFRIES-KELTON-HOUSE","metadata":{"station":"DUMFRIES KELTON HOUSE","gridRef":"NX989716","stationNo":"RR7315","lon":-3.58315,"lat":55.02861,"elevation":100,"counties":[]},"table":[[1870,1871,1872,1873,1874,1875,1876,1877,1878,1879],["3.95","3.15","6.83","6.47","","","","","",""],["-999","","2.48","1.12","","","","","",""],["-999","","3.77","4.23","","","","","",""],["-999","","-999","1.11","","","","","",""],["-999","","-999","0.62","","","","","",""],["1.55","2.15","5.54","1.52","","","","","",""],["1.1","5.1","4.22","5.19","","","","","",""],["1.65","2.83","3.64","5.98","","","","","",""],["3.97","2.17","4.69","2.55","","","","","",""],["6.59","3.99","3.81","6.1","","","","","",""],["1.93","3.19","5.96","2.37","","","","","",""],["1.84","4.43","6.46","1.49","","","","","",""],["32.61","","52.75","38.75","","","","","",""]],"structure":{"data":[],"external":[]},"comments":["MISFILED under TYRain_1860-1869_07_pt1 page 32"],"links":{"dataFile":"https://raw.githubusercontent.com/ed-hawkins/rainfall-rescue-data-v3/main/DATA/DUMFRIES-KELTON-HOUSE/DUMFRIES-KELTON-HOUSE.csv"},"history":[{"version":"working","location":"DUMFRIES-KELTON-HOUSE","name":"DUMFRIES-KELTON-HOUSE","changes":["New"]}]}