{"version":"working","name":"KENDAL-GOUGH","location":"KENDAL-GOUGH","metadata":{"station":"KENDAL observer J Gough","gridRef":"SD519929","stationNo":"RR390","lon":-2.7403,"lat":54.3299,"elevation":149,"counties":["Westmorland"]},"table":[[1780,1781,1782,1783,1784,1785,1786,1787,1788,1789,1790,1791,1792,1793,1794,1795,1796,1797,1798,1799],["","","","","","","","","5.82","6.9","6.84","8.03","3.76","6.37","7.3","","","","",""],["","","","","","","","","3.21","9.21","3.67","6.21","5.36","8.09","13.47","","","","",""],["","","","","","","","","3.16","1.15","1.52","3.41","6.49","4.57","4.53","","","","",""],["","","","","","","","","4.17","4.53","2.23","4.59","10.03","1.56","4.18","","","","",""],["","","","","","","","","1.29","5.56","2.46","4.2","6.3","1.88","2","","","","",""],["","","","","","","","3.64","2.54","4.24","3.98","3.26","3.65","3.35","1.46","","","","",""],["","","","","","","","5.55","7.74","5.22","7.68","6.19","5.71","3.59","4.16","","","","",""],["","","","","","","","5.46","3.29","1.49","6.34","4.83","7.21","6.68","5.34","","","","",""],["","","","","","","","2.23","5.7","5.87","6.71","3.04","10.83","2.4","7.67","","","","",""],["","","","","","","","8.87","2.35","6.42","4.86","5.17","5.78","5.35","7.33","","","","",""],["","","","","","","","4.53","3.43","6.25","5.01","6.58","5.74","3.61","6.01","","","","",""],["","","","","","","","4.9","1.01","13.94","9.82","7.84","12.69","7.24","6.2","","","","",""],["","","","","","","","","43.71","70.78","61.12","63.35","83.55","54.69","69.65","56.25","45.73","56.83","54.63","56.93"]],"structure":{"data":[{"startDate":"1780/01","endDate":"1789/13","filename":"TYRain_1677-1886_A_pt1-page-214.jpg"},{"startDate":"1790/01","endDate":"1799/13","filename":"TYRain_1677-1886_A_pt1-page-215.jpg"}],"external":[]},"comments":["ERROR_TYRain_1677-1886_A_pt1-page-215.csv CORRECTION: total 1795 recorded as 56.25","NGR at St George's Church which is at right elevation from the 1810 record from this site (another combined file)","but note that that record has NGR for the old Museum although elevation wrong"],"links":{"dataFile":"https://raw.githubusercontent.com/ed-hawkins/rainfall-rescue/working/DATA/KENDAL-GOUGH/KENDAL-GOUGH.csv"},"history":[{"version":"v1.0.0","name":"KENDAL-GOUGH","location":"KENDAL-GOUGH","changes":["New"]},{"version":"v1.1.0","name":"KENDAL-GOUGH","location":"KENDAL-GOUGH","changes":[]},{"version":"working","name":"KENDAL-GOUGH","location":"KENDAL-GOUGH","changes":[]}]}