{"version":"working","name":"LIDGATE","location":"LIDGATE","metadata":{"station":"LIDGATE","gridRef":"TL728575","stationNo":"1386/2","lon":0.52645,"lat":52.18867,"elevation":291,"counties":["Suffolk"]},"table":[[1951,1952,1953,1954,1955,1956,1957,1958,1959,1960],["","","","","","","","","",""],["","","","","","","","","",""],["","","","","","","","","",""],["","","","","","","","","","0.52"],["","","","","","","","","","0.72"],["","","","","","","","","","2.02"],["","","","","","","","","","3.46"],["","","","","","","","","","3.4"],["","","","","","","","","","3.96"],["","","","","","","","","","4.97"],["","","","","","","","","","2.71"],["","","","","","","","","","3.09"],["","","","","","","","","",""]],"structure":{"data":[{"startDate":"1951/01","endDate":"1960/13","filename":"TYRain_1951-1960_08_pt1-page-169.jpg"}],"external":[]},"comments":[],"links":{"dataFile":"https://raw.githubusercontent.com/ed-hawkins/rainfall-rescue-data-v2/main/DATA/LIDGATE/LIDGATE.csv"},"history":[{"version":"working","location":"LIDGATE","name":"LIDGATE","changes":["New"]}]}