{"version":"working","name":"TAUNTON-ASHLEIGH-2","location":"TAUNTON-ASHLEIGH","metadata":{"station":"TAUNTON-ASHLEIGH-(SECOND-GAUGE)","gridRef":"ST222254","stationNo":"RR8480","lon":-3.11062,"lat":51.02291,"elevation":78,"counties":["Somerset"]},"table":[[1900,1901,1902,1903,1904,1905,1906,1907,1908,1909],["","","","","2.91","0.68","4","1.07","0.71",""],["","","","","4.48","0.7","2.17","1","1.66",""],["","","","","1.89","3.59","1.12","0.56","2.57",""],["","","","","0.7","1.94","0.93","3.91","1.82",""],["","","","","1.64","0.17","2.6","2.45","1.39",""],["","","","","0.68","3.35","2.07","1.08","0.21",""],["","","","","3.54","0.37","0.48","1.77","1.27",""],["","","","","2.49","3.87","1.13","1.47","2.26",""],["","","","","1.43","1.18","0.44","0.34","2.49",""],["","","","","1","1.59","3.74","6.37","3.42",""],["","","","","1.55","2.7","3.49","2.51","1.03",""],["","","","","1.96","0.55","1.49","4.08","2.36",""],["","","","","24.27","20.69","23.66","26.61","21.19",""]],"structure":{"data":[{"startDate":"1900/01","endDate":"1909/13","filename":"TYRain_1900-1909_13_pt1-page-125.jpg"}],"external":[]},"comments":["Gauge 12.5 ft above ground and 14ft E of other gauge"],"links":{"dataFile":"https://raw.githubusercontent.com/ed-hawkins/rainfall-rescue-data-v3/main/DATA/TAUNTON-ASHLEIGH/TAUNTON-ASHLEIGH-2.csv"},"history":[{"version":"working","location":"TAUNTON-ASHLEIGH","name":"TAUNTON-ASHLEIGH-2","changes":["New"]}]}