{"version":"working","name":"WOLSINGHAM-DRYDERDALE-2","location":"WOLSINGHAM-DRYDERDALE","metadata":{"station":"WOLSINGHAM DRYDERDALE","gridRef":"NZ088331","stationNo":"3532/9","lon":-1.865,"lat":54.69286,"elevation":685,"counties":["Durham"]},"table":[[1951,1952,1953,1954,1955,1956,1957,1958,1959,1960],["","","","","","","","","",""],["","","","","","","","","",""],["","","","","","","","","",""],["","","","","","","","","",""],["","","","","","","","","",""],["","","","","","","","","",""],["","","","","","","","","",""],["","","","","","","","","",""],["","","","","","","","","",""],["","","","","","","","","",""],["","","","","","","","","",""],["","","","","","","","","","2.55"],["","","","","","","","","",""]],"structure":{"data":[{"startDate":"1951/01","endDate":"1959/13","filename":"TYRain_1951-1960_22_pt1-page-127.jpg"},{"startDate":"1960/02","endDate":"1960/10","filename":"TYRain_1951-1960_22_pt1-page-127.jpg"},{"startDate":"1960/12","endDate":"1960/12","filename":"TYRain_1951-1960_22_pt1-page-127.jpg"}],"external":[]},"comments":["only Dec 1960 value"],"links":{"dataFile":"https://raw.githubusercontent.com/ed-hawkins/rainfall-rescue/master/DATA/WOLSINGHAM-DRYDERDALE/WOLSINGHAM-DRYDERDALE-2.csv"},"history":[{"version":"v1.0.0","location":"WOLSINGHAM-DRYDERDALE","name":"WOLSINGHAM-DRYDERDALE-2","changes":["New"]},{"version":"v1.1.0","location":"WOLSINGHAM-DRYDERDALE","name":"WOLSINGHAM-DRYDERDALE-2","changes":[]},{"version":"working","location":"WOLSINGHAM-DRYDERDALE","name":"WOLSINGHAM-DRYDERDALE-2","changes":[]}]}