{"version":"v1.1.0","name":"ABERTILLERY-THE-PARK","gauges":[{"name":"ABERTILLERY-THE-PARK","ranges":[["1912/01","1960/12"]]}],"links":{"folder":"https://github.com/ed-hawkins/rainfall-rescue/tree/v1.1.0/DATA/ABERTILLERY-THE-PARK"},"history":[{"version":"v1.0.0","location":"ABERTILLERY-THE-PARK","changes":["New"]},{"version":"v1.1.0","location":"ABERTILLERY-THE-PARK","changes":[]},{"version":"v2.0.0","location":"ABERTILLERY-THE-PARK","changes":[]},{"version":"working","location":"ABERTILLERY-THE-PARK","changes":[]}]}