{"version":"v1.1.0","name":"LLANDRINDOD-WELLS-KIMBERLEY","gauges":[{"name":"LLANDRINDOD-WELLS-KIMBERLEY","ranges":[["1887/11","1893/12"],["1897/10","1906/12"],["1926/07","1937/11"]]},{"name":"LLANDRINDOD-WELLS-KIMBERLEY-2","ranges":[["1907/01","1926/06"]]}],"links":{"folder":"https://github.com/ed-hawkins/rainfall-rescue/tree/v1.1.0/DATA/LLANDRINDOD-WELLS-KIMBERLEY"},"history":[{"version":"v1.0.0","name":"LLANDRINDOD-WELLS-KIMBERLEY","changes":["New"]},{"version":"v1.1.0","name":"LLANDRINDOD-WELLS-KIMBERLEY","changes":[]}]}