{"version":"v1.0.0","name":"BROMYARD-ROWDEN-ABBEY","location":"BROMYARD-ROWDEN-ABBEY","metadata":{"station":"BROMYARD, ROWDEN ABBEY - old gauge","gridRef":"SO631563","stationNo":"RR1033","lon":-2.54136,"lat":52.20368,"elevation":455,"counties":["Herefordshire"]},"table":[[1890,1891,1892,1893,1894,1895,1896,1897,1898,1899,1900,1901,1902,1903,1904,1905,1906,1907,1908,1909],["","","","","","","","1.56","0.47","4.2","3.61","1.6","0.88","2.46","2.54","0.83","3.91","","",""],["","","","","","","","2.45","1.35","3.19","4.33","1.03","1.22","1.55","3.81","0.68","1.94","","",""],["","","","","","","","3.29","0.57","0.51","1.12","1.78","1.35","3.94","1.46","3.74","1.13","","",""],["","","","","","","","1.93","1.59","2.84","1.11","2.38","1.98","1.77","1.26","2.49","0.89","","",""],["","","","","","","","0.75","3.62","1.63","2.24","0.87","2.21","3.82","2.47","0.51","2.43","","",""],["","","","","","","","2.8","1.2","1.7","2.16","2.73","3.05","3.06","0.74","3.06","3.84","","",""],["","","","","","","","1.51","0.95","1.86","1.49","1.83","1.26","2.85","3.12","1.11","0.68","","",""],["","","","","","","","3.27","1.7","1.07","2.72","2.05","3.75","3.66","1.63","5.57","1.48","","",""],["","","","","","","","2.71","0.54","3.1","0.65","1.72","1.17","3.03","1.93","1.16","1.07","","",""],["","","","","","","","1.28","3.63","3.04","3.66","1.39","2.77","5.83","0.9","1.66","5.28","","",""],["","","","","","","","1.24","1.56","1.68","2.9","0.66","2.72","1.6","1.41","2.67","2.96","","",""],["","","","","","","","2.93","2.61","2.11","4.51","4.45","1.69","2.29","1.98","0.72","1.8","","",""],["","","","","","","","25.72","19.79","26.93","30.5","22.49","24.05","35.86","23.25","24.2","27.41","","",""]],"structure":{"data":[{"startDate":"1890/01","endDate":"1899/13","filename":"TYRain_1890-1899_12_pt1-page-036.jpg"},{"startDate":"1900/01","endDate":"1904/13","filename":"TYRain_1900-1909_15_pt1-page-049.jpg"},{"startDate":"1905/01","endDate":"1906/13","filename":"TYRain_1900-1909_15_pt1-page-050.jpg"},{"startDate":"1907/01","endDate":"1909/13","filename":"TYRain_1900-1909_15_pt1-page-049.jpg"}],"external":[]},"comments":[],"links":{"dataFile":"https://raw.githubusercontent.com/ed-hawkins/rainfall-rescue/v1.0.0/DATA/BROMYARD-ROWDEN-ABBEY/BROMYARD-ROWDEN-ABBEY.csv","imagesFolder":"https://drive.google.com/drive/folders/1vxo9O20JZn4JOPp9dggWPNvFpJ5lR6Yg"},"history":[{"version":"v1.0.0","location":"BROMYARD-ROWDEN-ABBEY","name":"BROMYARD-ROWDEN-ABBEY","changes":["New"]},{"version":"v1.1.0","location":"BROMYARD-ROWDEN-ABBEY","name":"BROMYARD-ROWDEN-ABBEY","changes":[]},{"version":"v2.0.0","location":"BROMYARD-ROWDEN-ABBEY","name":"BROMYARD-ROWDEN-ABBEY","changes":[]},{"version":"working","location":"BROMYARD-ROWDEN-ABBEY","name":"BROMYARD-ROWDEN-ABBEY","changes":[]}]}