{"version":"v1.0.0","name":"CHRISTCHURCH-MUDEFORD","location":"CHRISTCHURCH-MUDEFORD","metadata":{"station":"CHRISTCHURCH-MUDEFORD (MUDIEFORD HOUSE)","gridRef":"SZ179920","stationNo":"RR1681","lon":-1.7466,"lat":50.7282,"elevation":10,"counties":["Hampshire"]},"table":[[1860,1861,1862,1863,1864,1865,1866,1867,1868,1869],["","","","","1.59","5.24","","","",""],["","","","","1.2","2.88","","","",""],["","","","","3.16","1.11","","","",""],["","","","","1.64","0.69","","","",""],["","","","","1.09","3.22","","","",""],["","","","","2.17","1.34","","","",""],["","","","","0.28","1.84","","","",""],["","","","","1.08","2.68","","","",""],["","","","","2.6","0.02","","","",""],["","","","","1.41","","","","",""],["","","","","3.32","","","","",""],["","","","","2.44","","","","",""],["","","","","21.98","","","","",""]],"structure":{"data":[{"startDate":"1860/01","endDate":"1869/13","filename":"TYRain_1860-1869_01_pt3-page-015.jpg"}],"external":[]},"comments":[],"links":{"dataFile":"https://raw.githubusercontent.com/ed-hawkins/rainfall-rescue/v1.0.0/DATA/CHRISTCHURCH-MUDEFORD/CHRISTCHURCH-MUDEFORD.csv","imagesFolder":"https://drive.google.com/drive/folders/1XULAr9IFjtVGLXdXkGfEcDUVGbLtvOWg"},"history":[{"version":"v1.0.0","location":"CHRISTCHURCH-MUDEFORD","name":"CHRISTCHURCH-MUDEFORD","changes":["New"]},{"version":"v1.1.0","location":"CHRISTCHURCH-MUDEFORD","name":"CHRISTCHURCH-MUDEFORD","changes":[]},{"version":"v2.0.0","location":"CHRISTCHURCH-MUDEFORD","name":"CHRISTCHURCH-MUDEFORD","changes":[]}]}