{"version":"v1.0.0","name":"LEYBURN-2","location":"LEYBURN","metadata":{"station":"LEYBURN - MR PEARSON","gridRef":"SE111905","stationNo":"RR255","lon":-1.831,"lat":54.31,"elevation":650,"counties":["Yorkshire North Riding"]},"table":[[1880,1881,1882,1883,1884,1885,1886,1887,1888,1889],["0.15","0.43","3.26","","","","","","",""],["4.81","4.44","2.66","","","","","","",""],["1.50","3.46","2.74","","","","","","",""],["2.23","1.58","4.17","","","","","","",""],["2.57","0.90","2.04","","","","","","",""],["3.39","1.11","3.43","","","","","","",""],["5.49","4.01","4.64","","","","","","",""],["3.59","6.21","1.92","","","","","","",""],["6.15","4.11","4.03","","","","","","",""],["5.20","4.54","3.68","","","","","","",""],["2.90","5.20","5.20","","","","","","",""],["5.29","4.74","3.21","","","","","","",""],["43.27","40.73","40.98","","","","","","",""]],"structure":{"data":[{"startDate":"1880/01","endDate":"1889/13","filename":"TYRain_1880-1889_11_pt2-page-017.jpg"}],"external":[]},"comments":["No detailed location information found. The grid reference provided is for central Leyburn."],"links":{"dataFile":"https://raw.githubusercontent.com/ed-hawkins/rainfall-rescue/v1.0.0/DATA/LEYBURN/LEYBURN-2.csv","imagesFolder":"https://drive.google.com/drive/folders/1SnF2IVsYGpU5DmTqhdnGSQ0WdwdfSsnR"},"history":[{"version":"v1.0.0","location":"LEYBURN","name":"LEYBURN-2","changes":["New"]},{"version":"v1.1.0","location":"LEYBURN","name":"LEYBURN-2","changes":[]},{"version":"v2.0.0","location":"LEYBURN","name":"LEYBURN-2","changes":[]}]}