{"version":"v1.0.0","name":"PATNA-KERSE-FILTERS-3","location":"PATNA-KERSE-FILTERS","metadata":{"station":"PATNA (KERSE FILTERS) NEW SITE","gridRef":"NS425131","stationNo":"5259/2","lon":-4.48786,"lat":55.38651,"elevation":741,"counties":["Ayrshire"]},"table":[[1951,1952,1953,1954,1955,1956,1957,1958,1959,1960],["","","","","","","","","","4.73"],["","","","","","","","","","5"],["","","","","","","","","","2.02"],["","","","","","","","","","3.57"],["","","","","","","","","","1.72"],["","","","","","","","","","2.66"],["","","","","","","","","","4.05"],["","","","","","","","","","4.31"],["","","","","","","","","","3.54"],["","","","","","","","","","2.56"],["","","","","","","","","","8.35"],["","","","","","","","","","5.69"],["","","","","","","","","","48.2"]],"structure":{"data":[{"startDate":"1951/01","endDate":"1960/13","filename":"TYRain_1951-1960_26_pt1-page-283.jpg"}],"external":[]},"comments":[],"links":{"dataFile":"https://raw.githubusercontent.com/ed-hawkins/rainfall-rescue/v1.0.0/DATA/PATNA-KERSE-FILTERS/PATNA-KERSE-FILTERS-3.csv","imagesFolder":"https://drive.google.com/drive/folders/1PtvpDUDTpcyQhrEdZDYHCNOXJzVRTGbd"},"history":[{"version":"v1.0.0","location":"PATNA-KERSE-FILTERS","name":"PATNA-KERSE-FILTERS-3","changes":["New"]},{"version":"v1.1.0","location":"PATNA-KERSE-FILTERS","name":"PATNA-KERSE-FILTERS-3","changes":[]},{"version":"v2.0.0","location":"PATNA-KERSE-FILTERS","name":"PATNA-KERSE-FILTERS-3","changes":[]}]}