{"version":"v2.0.0","name":"ARDTALNAIG-OLD-SCHOOLHOUSE","location":"ARDTALNAIG-OLD-SCHOOLHOUSE","metadata":{"station":"ARDTALNAIG (OLD SCHOOLHOUSE)","gridRef":"NN701391","stationNo":"5556/59","lon":-4.1133,"lat":56.52593,"elevation":465,"counties":["Perthshire"]},"table":[[1951,1952,1953,1954,1955,1956,1957,1958,1959,1960],["","","","","","","","5.19","2.19","3.27"],["","","","","","","","3.05","1.55","6.24"],["","","","","","","","1.5","4.4","1.93"],["","","","","","","","1.69","4.51","5.3"],["","","","","","","","3.69","1.13","3.77"],["","","","","","","","4.08","2.56","2.34"],["","","","","","","3.74","4.64","5.57","2.96"],["","","","","","","4.79","5.8","2.28","3.89"],["","","","","","","2.37","5.14","1","4.16"],["","","","","","","3.43","3.94","5.87","7.34"],["","","","","","","1.63","1.14","8.67","7.73"],["","","","","","","7","8.73","11.48","6.41"],["","","","","","","","48.59","51.21","55.34"]],"structure":{"data":[{"startDate":"1951/01","endDate":"1960/13","filename":"TYRain_1951-1960_28_pt1-page-185.jpg"}],"external":[]},"comments":["Station no","5556/59","Midas","15115","Hyd Stn","861805"],"links":{"dataFile":"https://raw.githubusercontent.com/ed-hawkins/rainfall-rescue/v2.0.0/DATA/ARDTALNAIG-OLD-SCHOOLHOUSE/ARDTALNAIG-OLD-SCHOOLHOUSE.csv","imagesFolder":"https://drive.google.com/drive/folders/1gYizMOS1Yyo1T1_btcRTFVd34ouwr12k"},"history":[{"version":"v2.0.0","location":"ARDTALNAIG-OLD-SCHOOLHOUSE","name":"ARDTALNAIG-OLD-SCHOOLHOUSE","changes":["New"]}]}