{"version":"v2.0.0","name":"BRECON-LLANDEFAELOG-FACH-RECT-3","location":"BRECON-LLANDEFAELOG-FACH-RECT","metadata":{"station":"BRECON-LLANDEFAELOG-FACH-RECT-MVEABLE-GAUGE","gridRef":"SO033325","stationNo":"RR3205","lon":-3.40944,"lat":51.98251,"elevation":660,"counties":["Brecknockshire"]},"table":[[1890,1891,1892,1893,1894,1895,1896,1897,1898,1899],["","","","","","","","","1.91","6.36"],["","","","","","","","","3.08","5.19"],["","","","","","","","","1.7","1.4"],["","","","","","","","","2.24","4.09"],["","","","","","","","","4.58","2.67"],["","","","","","","","","2.45","1.64"],["","","","","","","","","1.43","0.88"],["","","","","","","","","3.73","1.56"],["","","","","","","","","0.86","4.13"],["","","","","","","","","5.58","4.6"],["","","","","","","","","3.09","3.61"],["","","","","","","","","5.27","3.41"],["","","","","","","","","35.92","39.54"]],"structure":{"data":[{"startDate":"1890/01","endDate":"1899/13","filename":"TYRain_1890-1899_19_pt1-page-214.jpg"}],"external":[]},"comments":["NGR is the rectory in Llandefaelog, the observer is a vicar and it has the correct relationship to the church. Altitudes match"],"links":{"dataFile":"https://raw.githubusercontent.com/ed-hawkins/rainfall-rescue/v2.0.0/DATA/BRECON-LLANDEFAELOG-FACH-RECT/BRECON-LLANDEFAELOG-FACH-RECT-3.csv","imagesFolder":"https://drive.google.com/drive/folders/1nqBtHRur-6MN85Xxtbt8tJmZtsPEEMK_"},"history":[{"version":"v1.0.0","location":"BRECON-LLANDEFAELOG-FACH-RECT","name":"BRECON-LLANDEFAELOG-FACH-RECT-3","changes":["New"]},{"version":"v1.1.0","location":"BRECON-LLANDEFAELOG-FACH-RECT","name":"BRECON-LLANDEFAELOG-FACH-RECT-3","changes":[]},{"version":"v2.0.0","location":"BRECON-LLANDEFAELOG-FACH-RECT","name":"BRECON-LLANDEFAELOG-FACH-RECT-3","changes":[]},{"version":"working","location":"BRECON-LLANDEFAELOG-FACH-RECT","name":"BRECON-LLANDEFAELOG-FACH-RECT-3","changes":[]}]}