{"version":"v2.0.0","name":"BRISTOL-REDLAND","location":"BRISTOL-REDLAND","metadata":{"station":"BRISTOL-REDLAND","gridRef":"ST579747","stationNo":"RR8189","lon":-2.60749,"lat":51.46969,"elevation":225,"counties":["Gloucestershire"]},"table":[[1880,1881,1882,1883,1884,1885,1886,1887,1888,1889,1890,1891,1892,1893,1894,1895,1896,1897,1898,1899],["","","","","4.4","3.22","3.77","1.98","1.19","1.18","3.54","","","","","","","","",""],["","","","","1.91","3.06","1.32","0.94","1.18","1.23","0.6","","","","","","","","",""],["","","","","1.98","0.64","3.32","3.83","3.13","3.72","0.98","","","","","","","","",""],["","","","","1.7","4.59","1.61","2.78","2.49","4.62","1.06","","","","","","","","",""],["","","","","2.45","3.11","4.71","1.32","0.96","2.73","1.92","","","","","","","","",""],["","","","","4.35","1.62","1.31","1.66","3.69","0.84","2.68","","","","","","","","",""],["","","","","3.37","0.96","3.22","1.02","6.05","3.88","4","","","","","","","","",""],["","","","","1.13","2.79","3.28","1.87","2.52","3.34","3.03","","","","","","","","",""],["","","","","2.69","3.97","2.53","4.11","0.77","2.21","0.92","","","","","","","","",""],["","","","","1.04","4.56","5.12","0.7","1.23","2.17","1.74","","","","","","","","",""],["","","","","1.2","5.73","3.89","4.95","5.81","1.29","2.61","","","","","","","","",""],["","","","","6.01","1.21","5.36","2.52","3.42","2.32","1.25","","","","","","","","",""],["","","","","32.23","35.46","39.44","27.68","32.44","29.53","24.33","","","","","","","","",""]],"structure":{"data":[{"startDate":"1880/01","endDate":"1889/13","filename":"TYRain_1880-1889_06_pt3-page-055.jpg"},{"startDate":"1890/01","endDate":"1899/13","filename":"TYRain_1890-1899_11_pt1-page-207.jpg"}],"external":[]},"comments":[],"links":{"dataFile":"https://raw.githubusercontent.com/ed-hawkins/rainfall-rescue/v2.0.0/DATA/BRISTOL-REDLAND/BRISTOL-REDLAND.csv","imagesFolder":"https://drive.google.com/drive/folders/17tzVVlYfsw1lT8I-ZRcy0rgj4_UYPzMp"},"history":[{"version":"v2.0.0","location":"BRISTOL-REDLAND","name":"BRISTOL-REDLAND","changes":["New"]}]}