{"version":"v2.0.0","name":"CEFN-COCH","location":"CEFN-COCH","metadata":{"station":"CEFN-COCH","gridRef":"SJ023007","stationNo":"4250/9","lon":-3.44379,"lat":52.59528,"elevation":855,"counties":["Montgomeryshire"]},"table":[[1951,1952,1953,1954,1955,1956,1957,1958,1959,1960],["","","","","","","","","",""],["","","","","","","","","",""],["","","","","","","","","",""],["","","","","","","","","",""],["","","","","","","","","",""],["","","","","","","","","",""],["","","","","","","","","",""],["","","","","","","","","",""],["","","","","","","","","","4.99"],["","","","","","","","","","7.13"],["","","","","","","","","","8.44"],["","","","","","","","","","8.65"],["","","","","","","","","",""]],"structure":{"data":[{"startDate":"1951/01","endDate":"1960/13","filename":"TYRain_1951-1960_24_pt1-page-032.jpg"}],"external":[]},"comments":["NGR is from 1950s record. Altitudes match but the location is 2 miles SW of place called Cefn Coch.","MIDAS src_id 9696 ends 1983 but starts 1961, perhaps based on the first full year"],"links":{"dataFile":"https://raw.githubusercontent.com/ed-hawkins/rainfall-rescue/v2.0.0/DATA/CEFN-COCH/CEFN-COCH.csv","imagesFolder":"https://drive.google.com/drive/folders/1vgXUwYaX5iLi8S-GiFNGNNKaqOOToS20"},"history":[{"version":"v2.0.0","location":"CEFN-COCH","name":"CEFN-COCH","changes":["New"]}]}