{"version":"v2.0.0","name":"CLAPHAM-PARK-NEW-PARK-ROAD-2","location":"CLAPHAM-PARK-NEW-PARK-ROAD","metadata":{"station":"CLAPHAM-PARK-NEW-PARK-ROAD-(ATKINS-ROAD)","gridRef":"TQ300737","stationNo":"RR8072","lon":-0.13046,"lat":51.44769,"elevation":120,"counties":["London County"]},"table":[[1906,1907,1908,1909,1910,1911,1912,1913,1914,1915,1916,1917,1918,1919],["","0.8","1.27","0.82","1.48","","","","","","","","",""],["","1.02","","0.5","2.5","","","","","","","","",""],["1.11","0.74","","2.62","0.91","","","","","","","","",""],["0.66","3.88","1.94","1.59","1.78","","","","","","","","",""],["1.36","2.14","1.9","1.38","2.03","","","","","","","","",""],["2.89","3.13","2.62","3.63","2.68","","","","","","","","",""],["1.44","1.29","3.72","3.26","2.75","","","","","","","","",""],["0.78","2.13","3.32","1.64","2.45","","","","","","","","",""],["2.33","0.68","1.12","2.47","0.64","","","","","","","","",""],["3.04","3.25","2.2","3.91","2.37","","","","","","","","",""],["4.68","2.22","0.63","0.99","2.83","","","","","","","","",""],["2.29","2.85","1.83","2.16","2.68","","","","","","","","",""],["","24.13","","24.97","25.1","","","","","","","","",""]],"structure":{"data":[{"startDate":"1906/03","endDate":"1906/12","filename":"TYRain_1900-1909_01_pt1-page-017.jpg"},{"startDate":"1907/01","endDate":"1909/13","filename":"TYRain_1900-1909_01_pt1-page-017.jpg"},{"startDate":"1910/01","endDate":"1919/13","filename":"TYRain_1910-1919_01_pt1-page-018.jpg"}],"external":[]},"comments":["Exact house unknown but distances and moves make it at S end of Atkins Road","1906 Mar 1 Gauge moved 1000ft NNE from New Park Road","1908 Feb Mar Owing to illness observations very unreliable"],"links":{"dataFile":"https://raw.githubusercontent.com/ed-hawkins/rainfall-rescue/v2.0.0/DATA/CLAPHAM-PARK-NEW-PARK-ROAD/CLAPHAM-PARK-NEW-PARK-ROAD-2.csv","imagesFolder":"https://drive.google.com/drive/folders/1YkqUej2wRkF6W7AmcW1uL3HR9ccukzvt"},"history":[{"version":"v2.0.0","location":"CLAPHAM-PARK-NEW-PARK-ROAD","name":"CLAPHAM-PARK-NEW-PARK-ROAD-2","changes":["New"]}]}