{"version":"v2.0.0","name":"CREDITON-SHOBROOKE-HOUSE","location":"CREDITON-SHOBROOKE-HOUSE","metadata":{"station":"CREDITON-SHOBROOKE-HOUSE","gridRef":"SS860011","stationNo":"1784/1","lon":-3.61842,"lat":50.79822,"elevation":360,"counties":["Devon"]},"table":[[1951,1952,1953,1954,1955,1956,1957,1958,1959,1960],["","","","1.66","4.9","3.75","2.96","3.1","4.32","3.47"],["","","","2.95","3.05","0.35","4.65","3.65","0.34","3.26"],["","","","2.55","1.27","1.17","2.35","1.26","3.68","2.84"],["","","","0.25","0.99","1.26","0.18","0.63","3.19","2.95"],["","","","2.57","3.26","0.71","1.54","3.02","1.39","2.66"],["","","","3.59","3.02","1.9","3.01","3.68","2.07","0.93"],["","","","2.67","1.64","4.84","3.26","2.64","2.09","4.82"],["","","","2.24","0.83","2.88","2.52","3.82","2.66","4.22"],["","","","2.6","1.45","6.14","3.19","3.83","0.3","5.84"],["","","","2.13","1.31","2","2.23","3.02","3.42","10.88"],["","","","5.43","3.17","2.1","2.37","3.58","6.55","3.93"],["","","0.87","3.78","5.38","4.17","2.96","4.79","6.26","4.65"],["","","","32.42","30.27","31.27","31.22","37.02","36.27","50.45"]],"structure":{"data":[{"startDate":"1951/01","endDate":"1960/13","filename":"TYRain_1951-1960_10_pt1-page-206.jpg"}],"external":[]},"comments":["Post 1960 known as Shobrooke House SRC_ID 8300","1954-1972"],"links":{"dataFile":"https://raw.githubusercontent.com/ed-hawkins/rainfall-rescue/v2.0.0/DATA/CREDITON-SHOBROOKE-HOUSE/CREDITON-SHOBROOKE-HOUSE.csv","imagesFolder":"https://drive.google.com/drive/folders/1piFbAb0KY7hgAibxXzY0R0zTWftRniCh"},"history":[{"version":"v2.0.0","location":"CREDITON-SHOBROOKE-HOUSE","name":"CREDITON-SHOBROOKE-HOUSE","changes":["New"]}]}