{"version":"v2.0.0","name":"ETWALL-HALL","location":"ETWALL-HALL","metadata":{"station":"ETWALL-HALL","gridRef":"SK267320","stationNo":"2652","lon":-1.60466,"lat":52.8848,"elevation":235,"counties":["Derbyshire"]},"table":[[1920,1921,1922,1923,1924,1925,1926,1927,1928,1929,1930,1931,1932,1933,1934,1935,1936,1937,1938,1939,1940],["","","","","","","","","","","","2.61","2.16","2.04","2.59","0.88","3.42","3.31","2.49","",""],["","","","","","","","","","","","3.02","0.32","3.66","0.35","2.35","1.76","4.43","0.79","",""],["","","","","","","","","","","","0.11","1.74","2.47","1.78","0.67","1.47","2.64","0.94","",""],["","","","","","","","","","","","3.45","2.87","1","1.89","2.74","1.57","1.98","0.15","",""],["","","","","","","","","","","","2.7","6.81","1.82","0.82","0.48","0.3","2.29","1.38","",""],["","","","","","","","","","","","3.4","0.64","2.58","0.67","3.79","3.47","0.96","2.33","",""],["","","","","","","","","","","","3.78","3.21","2.33","1.17","0.5","3.87","2.59","3.62","",""],["","","","","","","","","","","","5.22","2.49","0.83","2.1","2.14","0.91","0.46","2.15","",""],["","","","","","","","","","","","3.8","2.47","1.82","2.04","3.41","2.75","1.42","4.11","",""],["","","","","","","","","","","","0.89","3.56","5.79","2.06","3.45","1.76","2.07","3.15","",""],["","","","","","","","","","","","3.32","2.04","1.2","1.85","4.69","2.52","1.76","3.08","",""],["","","","","","","","","","","","1.19","0.9","0.37","4.54","4.07","2.29","2.68","2.56","",""],["","","","","","","","","","23.87","36.08","33.49","29.21","25.91","21.86","29.17","26.09","26.59","26.75","",""]],"structure":{"data":[{"startDate":"1931/01","endDate":"1940/13","filename":"TYRain_1931-1940_16_pt1-page-005.jpg"}],"external":[{"startDate":"1929/13","endDate":"1929/13","comment":"Data from British Rainfall 1929"},{"startDate":"1930/13","endDate":"1930/13","comment":"Data from British Rainfall 1930"}]},"comments":["NGR is Etwall Hall. Stated altitude appears to be 20 ft. too high","1929 and 1930 totals are from British Rainfall; record sheet not found"],"links":{"dataFile":"https://raw.githubusercontent.com/ed-hawkins/rainfall-rescue/v2.0.0/DATA/ETWALL-HALL/ETWALL-HALL.csv","imagesFolder":"https://drive.google.com/drive/folders/1tsXZ8LDRC9nEPP73LKbAR3R7J7jATA8G"},"history":[{"version":"v2.0.0","location":"ETWALL-HALL","name":"ETWALL-HALL","changes":["New"]}]}