{"version":"v2.0.0","name":"FOUR-CROSSES-COUNCIL-SCHOOL","location":"FOUR-CROSSES-COUNCIL-SCHOOL","metadata":{"station":"FOUR-CROSSES-COUNCIL-SCHOOL","gridRef":"SH3973539195","stationNo":"RR8805","lon":-4.38558,"lat":52.92618,"elevation":200,"counties":["Caernarfonshire"]},"table":[[1910,1911,1912,1913,1914,1915,1916,1917,1918,1919,1920,1921,1922,1923,1924,1925,1926,1927,1928,1929,1930],["","","","","","","","","5.62","","6.28","5.91","5.81","3.82","","","","","","",""],["","","","","","","","","4.78","","4.25","0.39","5.91","8.14","","","","","","",""],["","","","","","","","","1.86","","8.4","6.94","3.62","1.25","","","","","","",""],["","","","","","","","","3.03","","6.22","1.17","3.96","3.63","","","","","","",""],["","","","","","","","","5.76","","6.13","3.7","3.13","2.8","","","","","","",""],["","","","","","","","","3.51","","3.15","0.84","1.16","1.33","","","","","","",""],["","","","","","","","","2.11","","7.93","4.02","5.2","","","","","","","",""],["","","","","","","","","2.81","","4.66","","2.68","","","","","","","",""],["","","","","","","","","10.04","","6.69","2.42","6.55","6.88","","","","","","",""],["","","","","","","","","5.84","","5.13","4.94","1.82","8.23","","","","","","",""],["","","","","","","","","1.7","","3.3","3.14","4.24","7.51","","","","","","",""],["","","","","","","","","9.8","","3.53","6.57","6.95","","","","","","","",""],["","","","","","","","","56.86","","65.67","","51.03","","","","","","","",""]],"structure":{"data":[{"startDate":"1910/01","endDate":"1919/13","filename":"TYRain_1910-1919_24_pt1-page-239.jpg"},{"startDate":"1920/01","endDate":"1921/07","filename":"TYRain_1920-1930_28_pt1-page-065.jpg"},{"startDate":"1921/09","endDate":"1921/12","filename":"TYRain_1920-1930_28_pt1-page-065.jpg"},{"startDate":"1922/01","endDate":"1923/06","filename":"TYRain_1920-1930_28_pt1-page-065.jpg"},{"startDate":"1923/09","endDate":"1923/11","filename":"TYRain_1920-1930_28_pt1-page-065.jpg"},{"startDate":"1924/01","endDate":"1930/13","filename":"TYRain_1920-1930_28_pt1-page-065.jpg"}],"external":[]},"comments":["1921 Aug estimated","1923 Jul Aug Dec estimated"],"links":{"dataFile":"https://raw.githubusercontent.com/ed-hawkins/rainfall-rescue/v2.0.0/DATA/FOUR-CROSSES-COUNCIL-SCHOOL/FOUR-CROSSES-COUNCIL-SCHOOL.csv","imagesFolder":"https://drive.google.com/drive/folders/162YC6AspgoqadKjy9acPZGirj-TcN960"},"history":[{"version":"v2.0.0","location":"FOUR-CROSSES-COUNCIL-SCHOOL","name":"FOUR-CROSSES-COUNCIL-SCHOOL","changes":["New"]}]}