{"version":"v2.0.0","name":"INVERNESS-MIX-2","location":"INVERNESS-MIX","metadata":{"station":"INVERNESS (FRASER PARK)","gridRef":"NH675448","stationNo":"5701/6/1/7","lon":-4.21113,"lat":57.47404,"elevation":103,"counties":["Inverness"]},"table":[[1951,1952,1953,1954,1955,1956,1957,1958,1959,1960],["","","","","","","3.27","1.98","",""],["","","","","","","2.56","1.7","",""],["","","","","","","3.1","1.05","",""],["","","","","","","0.68","1.49","",""],["","","","","","","1.74","2.61","",""],["","","","","","","6.27","1.29","",""],["","","","","","","","","",""],["","","","","","","3.71","","",""],["","","","","","","1.4","","",""],["","","","","","","1.78","","",""],["","","","","","","1.5","","",""],["","","","","","","3.04","","",""],["","","","","","","","","",""]],"structure":{"data":[{"startDate":"1951/01","endDate":"1960/13","filename":"TYRain_1951-1960_30_pt1-page-166.jpg"}],"external":[]},"comments":["Station no","5701/6/1/7","Midas","14688","Hyd Stn","805470"],"links":{"dataFile":"https://raw.githubusercontent.com/ed-hawkins/rainfall-rescue/v2.0.0/DATA/INVERNESS-MIX/INVERNESS-MIX-2.csv","imagesFolder":"https://drive.google.com/drive/folders/1Wj8-EJsS_vMv7IW0XB5zpjMBnxx5b77C"},"history":[{"version":"v2.0.0","location":"INVERNESS-MIX","name":"INVERNESS-MIX-2","changes":["New"]}]}