{"version":"v2.0.0","name":"LINDFIELD-GRAVELYE-2","location":"LINDFIELD-GRAVELYE","metadata":{"station":"LINDFIELD-GRAVELYE","gridRef":"TQ348242","stationNo":"RR4900","lon":-0.08024,"lat":51.00141,"elevation":170,"counties":["Sussex"]},"table":[[1910,1911,1912,1913,1914,1915,1916,1917,1918,1919],["","","","","1.01","","","","",""],["","","","","4.64","","","","",""],["","","","","5.4","","","","",""],["","","","","1.88","","","","",""],["","","","","1.12","","","","",""],["","","","","0.7","","","","",""],["","","","","2.09","","","","",""],["","","","","0.91","","","","",""],["","","","","1.32","","","","",""],["","","","","2.28","","","","",""],["","","","","4.18","","","","",""],["","","","","8.27","","","","",""],["","","","","33.8","","","","",""]],"structure":{"data":[{"startDate":"1910/01","endDate":"1914/13","filename":"TYRain_1910-1919_04_pt1-page-143.jpg"}],"external":[]},"comments":["1915 Gauge move"],"links":{"dataFile":"https://raw.githubusercontent.com/ed-hawkins/rainfall-rescue/v2.0.0/DATA/LINDFIELD-GRAVELYE/LINDFIELD-GRAVELYE-2.csv","imagesFolder":"https://drive.google.com/drive/folders/11ZUU_GF8JR8xNEa8MxRKJStWbIV6hnRf"},"history":[{"version":"v2.0.0","location":"LINDFIELD-GRAVELYE","name":"LINDFIELD-GRAVELYE-2","changes":["New"]}]}