{"version":"v2.0.0","name":"LLANDYSSILIOGOGO-DOLWYLAN","location":"LLANDYSSILIOGOGO-DOLWYLAN","metadata":{"station":"LLANDYSSILIOGOGO-DOLWYLAN","gridRef":"SN356573","stationNo":"4123/7/8","lon":-4.40642,"lat":52.18937,"elevation":90,"counties":["Cardiganshire"]},"table":[[1951,1952,1953,1954,1955,1956,1957,1958,1959,1960],["","","","","2.41","3.69","3.02","3.9","5.38",""],["","","","","2.53","0.57","2.99","4.25","0.32",""],["","","","","3.48","1.37","2.79","0.89","3.81",""],["","","","","2.26","1.15","0.28","0.67","3.63",""],["","","","","3.12","0.83","2.05","4.58","1.65",""],["","","","","3.94","2.12","1.13","3.32","2.07",""],["","","","","0.56","3.44","3.55","4.26","2.75",""],["","","","","1.42","4.48","2.64","3.3","0.4",""],["","","","","2.21","4.35","6.87","7.54","0.38",""],["","","","","2.98","2.38","3.43","3.6","6.72",""],["","","","","2.39","2.07","2.21","3.31","8.71",""],["","","","","3.96","4.49","2.9","3.62","5.71",""],["","","","","31.26","30.94","33.86","43.24","41.53",""]],"structure":{"data":[{"startDate":"1951/01","endDate":"1960/13","filename":"TYRain_1951-1960_23_pt1-page-155.jpg"}],"external":[]},"comments":[],"links":{"dataFile":"https://raw.githubusercontent.com/ed-hawkins/rainfall-rescue/v2.0.0/DATA/LLANDYSSILIOGOGO-DOLWYLAN/LLANDYSSILIOGOGO-DOLWYLAN.csv","imagesFolder":"https://drive.google.com/drive/folders/177NkPviDly9Q7Lzu5i1ygkonamw0cyLr"},"history":[{"version":"v2.0.0","location":"LLANDYSSILIOGOGO-DOLWYLAN","name":"LLANDYSSILIOGOGO-DOLWYLAN","changes":["New"]}]}