{"version":"working","name":"BIRMINGHAM-SELLY-OAK-LODGE-HILL","gauges":[{"name":"BIRMINGHAM-SELLY-OAK-LODGE-HILL","ranges":[["1896/01","1916/12"],["1918/01","1921/12"],["1923/01","1930/12"]]}],"links":{"TYRSheets":"https://github.com/ed-hawkins/rainfall-rescue/blob/working/DATA/BIRMINGHAM-SELLY-OAK-LODGE-HILL/BIRMINGHAM-SELLY-OAK-LODGE-HILL.pdf"},"history":[{"version":"v1.0.0","name":"BIRMINGHAM-SELLY-OAK-LODGE-HILL","changes":["New"]},{"version":"v1.1.0","name":"BIRMINGHAM-SELLY-OAK-LODGE-HILL","changes":[]},{"version":"working","name":"BIRMINGHAM-SELLY-OAK-LODGE-HILL","changes":[]}]}