{"version":"working","name":"BUXTED-STRAWBERRY-HALL","gauges":[{"name":"BUXTED-STRAWBERRY-HALL","ranges":[["1888/01","1939/12"]]}],"links":{"folder":"https://github.com/ed-hawkins/rainfall-rescue/tree/master/DATA/BUXTED-STRAWBERRY-HALL"},"history":[{"version":"v1.0.0","location":"BUXTED-STRAWBERRY-HALL","changes":["New"]},{"version":"v1.1.0","location":"BUXTED-STRAWBERRY-HALL","changes":[]},{"version":"v2.0.0","location":"BUXTED-STRAWBERRY-HALL","changes":[]},{"version":"working","location":"BUXTED-STRAWBERRY-HALL","changes":[]}]}