{"version":"working","name":"FALMOUTH-FLUSHING-TREFUSIS","gauges":[{"name":"FALMOUTH-FLUSHING-TREFUSIS","ranges":[["1894/06","1895/09"]]},{"name":"FALMOUTH-FLUSHING-TREFUSIS-2","ranges":[["1895/10","1899/05"],["1899/08","1900/12"],["1922/07","1942/12"]]}],"links":{"folder":"https://github.com/ed-hawkins/rainfall-rescue/tree/master/DATA/FALMOUTH-FLUSHING-TREFUSIS"},"history":[{"version":"v1.0.0","location":"FALMOUTH-FLUSHING-TREFUSIS","changes":["New"]},{"version":"v1.1.0","location":"FALMOUTH-FLUSHING-TREFUSIS","changes":[]},{"version":"working","location":"FALMOUTH-FLUSHING-TREFUSIS","changes":[]}]}