{"version":"working","name":"SHOEBURYNESS","gauges":[{"name":"SHOEBURYNESS","ranges":[["1865/06","1918/04"],["1920/01","1960/12"]]},{"name":"SHOEBURYNESS-2","ranges":[["1900/01","1919/12"]]}],"links":{"folder":"https://github.com/ed-hawkins/rainfall-rescue/tree/master/DATA/SHOEBURYNESS"},"history":[{"version":"v1.0.0","location":"SHOEBURYNESS","changes":["New"]},{"version":"v1.1.0","location":"SHOEBURYNESS","changes":[]},{"version":"v2.0.0","location":"SHOEBURYNESS","changes":[]},{"version":"working","location":"SHOEBURYNESS","changes":[]}]}