{"version":"working","name":"WEST-BUCKLAND-SCHOOL","gauges":[{"name":"WEST-BUCKLAND-SCHOOL","ranges":[["1906/01","1906/01"],["1907/01","1909/12"],["1913/09","1913/09"],["1914/03","1914/03"],["1914/05","1915/03"],["1915/05","1916/01"],["1916/08","1916/08"],["1919/12","1919/12"],["1920/02","1920/06"],["1921/01","1921/12"],["1922/02","1922/12"],["1923/02","1923/04"],["1923/06","1923/06"],["1923/08","1923/09"],["1923/12","1924/06"],["1924/08","1924/11"],["1925/01","1925/06"],["1925/09","1926/02"],["1926/04","1926/06"],["1926/09","1926/09"],["1926/11","1926/12"],["1935/01","1936/12"],["1940/01","1958/10"],["1958/12","1960/12"]]}],"links":{"TYRSheets":"https://github.com/ed-hawkins/rainfall-rescue/blob/working/DATA/WEST-BUCKLAND-SCHOOL/WEST-BUCKLAND-SCHOOL.pdf"},"history":[{"version":"v1.0.0","name":"WEST-BUCKLAND-SCHOOL","changes":["New"]},{"version":"v1.1.0","name":"WEST-BUCKLAND-SCHOOL","changes":[]},{"version":"working","name":"WEST-BUCKLAND-SCHOOL","changes":[]}]}