{"version":"v1.1.0","name":"COWES-STEPHENSON-ROAD-2","location":"COWES-STEPHENSON-ROAD","metadata":{"station":"COWES-STEPHENSON-ROAD-(JAEDCOT-NEW-GAUGE)","gridRef":"SZ496956","stationNo":"RR3111","lon":-1.2977,"lat":50.7584,"elevation":72,"counties":["Isle of Wight"]},"table":[[1900,1901,1902,1903,1904,1905,1906,1907,1908,1909],["","","0.75","1.9","3.47","0.86","","","",""],["","","1.4","1.77","3.57","0.31","","","",""],["","","2.5","2.65","1.25","5.1","","","",""],["","","1.25","2.61","1.58","1.88","","","",""],["","","1.75","2.47","3.32","0.45","","","",""],["","","2.64","2.75","1.15","3.99","","","",""],["","","1.62","1.95","1.25","0.4","","","",""],["","","4.1","2.9","2.86","2.51","","","",""],["","","1.2","2.33","2.01","2.62","","","",""],["","","2.16","7.64","2.4","2.16","","","",""],["","","3.18","1.6","1.1","4.52","","","",""],["","","1.8","2.5","3.07","0.72","","","",""],["","","24.35","33.07","27.03","25.52","","","",""]],"structure":{"data":[{"startDate":"1900/01","endDate":"1909/13","filename":"TYRain_1900-1909_05_pt1-page-161.jpg"}],"external":[]},"comments":["Jaedcot, 2 Bernard Road in 1904 - on west side counting from north end","This was a home made gauge - the observer was a 'technical maker for glass'","These years appear on 2 sheets with major differences in 1902 only so taken to be an overlap year having built a new gauge","1906 Jan Gauge moved 1/4m SW to Stephenson Road"],"links":{"dataFile":"https://raw.githubusercontent.com/ed-hawkins/rainfall-rescue/v1.1.0/DATA/COWES-STEPHENSON-ROAD/COWES-STEPHENSON-ROAD-2.csv","imagesFolder":"https://drive.google.com/drive/folders/1E6FFJrGV4a1vNl-GSPlo5sBmy16_A7iv"},"history":[{"version":"v1.0.0","location":"COWES-STEPHENSON-ROAD","name":"COWES-STEPHENSON-ROAD-2","changes":["New"]},{"version":"v1.1.0","location":"COWES-STEPHENSON-ROAD","name":"COWES-STEPHENSON-ROAD-2","changes":[]},{"version":"v2.0.0","location":"COWES-STEPHENSON-ROAD","name":"COWES-STEPHENSON-ROAD-2","changes":[]},{"version":"working","location":"COWES-STEPHENSON-ROAD","name":"COWES-STEPHENSON-ROAD-2","changes":[]}]}