{"version":"v1.1.0","name":"LLANWRTYD-WELLS-LLANDULAS-2","location":"LLANWRTYD-WELLS-LLANDULAS","metadata":{"station":"LLANWRTYD-WELLS-LLANDULAS-SCHOOL","gridRef":"SN878413","stationNo":"4208/6","lon":-3.63792,"lat":52.05868,"elevation":780,"counties":["Brecknockshire"]},"table":[[1931,1932,1933,1934,1935,1936,1937,1938,1939,1940,1941,1942,1943,1944,1945,1946,1947,1948,1949,1950],["","","","","","","","","","3.55","4.59","4.9","8.67","","4.16","8.73","","","",""],["","","","","","","","","","4.19","4.22","1.36","5.98","2.23","6.9","","","","",""],["","","","","","","","","","4.44","3.95","4.89","1.37","0.95","4.68","","","","",""],["","","","","","","","","","4.62","1.81","2.42","1.55","2.04","3.47","","","","",""],["","","","","","","","","","2.44","2.99","5.49","4.37","1.47","4.02","","","","",""],["","","","","","","","","4.85","1.94","2.61","0.66","4.95","3.68","7","","","","",""],["","","","","","","","","11.53","4.71","2.33","7.62","4.02","2.81","","","","","",""],["","","","","","","","","4.48","1.94","","5.76","6.92","2.8","","","","","",""],["","","","","","","","","1.59","2.95","1.05","","7.08","5.47","","","","","",""],["","","","","","","","","3.2","5.1","6.05","6.53","8.6","7.25","5.35","","","","",""],["","","","","","","","","12.39","10.99","3.01","1.11","7.14","9.45","","","","","",""],["","","","","","","","","4.73","4.73","3.59","9.19","2.11","5.65","","","","","",""],["","","","","","","","","","51.6","","","62.76","","","","","","",""]],"structure":{"data":[{"startDate":"1931/01","endDate":"1940/13","filename":"TYRain_1931-1940_22_pt1-page-121.jpg"},{"startDate":"1941/01","endDate":"1941/07","filename":"TYRain_1941-1950_26_pt1-page-085.jpg"},{"startDate":"1941/09","endDate":"1941/12","filename":"TYRain_1941-1950_26_pt1-page-085.jpg"},{"startDate":"1942/01","endDate":"1942/08","filename":"TYRain_1941-1950_26_pt1-page-085.jpg"},{"startDate":"1942/10","endDate":"1942/12","filename":"TYRain_1941-1950_26_pt1-page-085.jpg"},{"startDate":"1943/01","endDate":"1943/13","filename":"TYRain_1941-1950_26_pt1-page-085.jpg"},{"startDate":"1944/02","endDate":"1944/12","filename":"TYRain_1941-1950_26_pt1-page-085.jpg"},{"startDate":"1945/01","endDate":"1949/05","filename":"TYRain_1941-1950_26_pt1-page-085.jpg"},{"startDate":"1949/13","endDate":"1949/13","filename":"TYRain_1941-1950_26_pt1-page-085.jpg"},{"startDate":"1950/09","endDate":"1950/13","filename":"TYRain_1941-1950_26_pt1-page-085.jpg"}],"external":[]},"comments":["NGR is near school as described in record. Altitudes match. Gauge moved 0.25 miles N in 1949","Jan and Feb 1940 and Jan 1941 corrected for snow; left in this record"],"links":{"dataFile":"https://raw.githubusercontent.com/ed-hawkins/rainfall-rescue/v1.1.0/DATA/LLANWRTYD-WELLS-LLANDULAS/LLANWRTYD-WELLS-LLANDULAS-2.csv","imagesFolder":"https://drive.google.com/drive/folders/1VV5phrRBLeW_sQkNp63IEC7MdLwY_TtB"},"history":[{"version":"v1.0.0","name":"LLANWRTYD-WELLS-LLANDULAS-2","location":"LLANWRTYD-WELLS-LLANDULAS","changes":["New"]},{"version":"v1.1.0","name":"LLANWRTYD-WELLS-LLANDULAS-2","location":"LLANWRTYD-WELLS-LLANDULAS","changes":[]}]}