{"version":"v1.1.0","name":"LOCH-EIL-ACHDALIEU-2","location":"LOCH-EIL-ACHDALIEU","metadata":{"station":"LOCH EIL (ACHDALIEU)","gridRef":"NN060782","stationNo":"5722","lon":-5.18331,"lat":56.85458,"elevation":100,"counties":["Inverness"]},"table":[[1951,1952,1953,1954,1955,1956,1957,1958,1959,1960],["","","","","","","12.36","9.67","3.54","4.63"],["","","","","","","3.93","3.68","3.62","6.78"],["","","","","","","6.86","1.53","5.78","0.78"],["","","","","","","1.53","4.53","5.65","6.21"],["","","","","","","1.83","5.17","1.52","2.59"],["","","","","","","3.42","2.3","4.83","3.58"],["","","","","","5.53","6.13","2.78","6.89","4.49"],["","","","","","5","5.49","4.73","5.4","5.25"],["","","","","","8.12","3.12","5.64","3.06","3.11"],["","","","","","6.26","9.12","9.75","8.5","1.05"],["","","","","","7.42","2.12","1.68","9.74","7.41"],["","","","","","11.9","10.35","6.23","11.13","9.47"],["","","","","","","66.26","57.69","69.66","55.35"]],"structure":{"data":[{"startDate":"1951/01","endDate":"1960/13","filename":"TYRain_1951-1960_30_pt1-page-258.jpg"}],"external":[]},"comments":["1959 total changed to match sum of monthly values"],"links":{"dataFile":"https://raw.githubusercontent.com/ed-hawkins/rainfall-rescue/v1.1.0/DATA/LOCH-EIL-ACHDALIEU/LOCH-EIL-ACHDALIEU-2.csv","imagesFolder":"https://drive.google.com/drive/folders/1PsKWUccxGPiso74pSnrwr7xuoBAq5VTh"},"history":[{"version":"v1.0.0","location":"LOCH-EIL-ACHDALIEU","name":"LOCH-EIL-ACHDALIEU-2","changes":["New"]},{"version":"v1.1.0","location":"LOCH-EIL-ACHDALIEU","name":"LOCH-EIL-ACHDALIEU-2","changes":[]},{"version":"working","location":"LOCH-EIL-ACHDALIEU","name":"LOCH-EIL-ACHDALIEU-2","changes":[]}]}