{"version":"v1.1.0","name":"LOWER-RIVINGTON-2","location":"LOWER-RIVINGTON","metadata":{"station":"HORWICH (LOWER RIVINGTON) NEW GAUGE","gridRef":"SD631126","stationNo":"2996/1","lon":-2.55918,"lat":53.60865,"elevation":440,"counties":["Lancashire"]},"table":[[1941,1942,1943,1944,1945,1946,1947,1948,1949,1950,1951,1952,1953,1954,1955,1956,1957,1958,1959,1960],["","","","","","","","","","3.12","4.22","","","","","","","","",""],["","","","","","","","","","5.29","3.42","","","","","","","","",""],["","","","","","","","","","2.15","5.05","","","","","","","","",""],["","","","","","","","","","2.97","2.25","","","","","","","","",""],["","","","","","","","","","2.07","3.03","","","","","","","","",""],["","","","","","","","","","2.85","1.78","","","","","","","","",""],["","","","","","","","","","4.55","3.22","","","","","","","","",""],["","","","","","","","","","6.98","5.14","","","","","","","","",""],["","","","","","","","","","7.84","3.48","","","","","","","","",""],["","","","","","","","","","3.49","0.76","","","","","","","","",""],["","","","","","","","","","6.61","9","","","","","","","","",""],["","","","","","","","","5.5","3.68","8.35","","","","","","","","",""],["","","","","","","","","","51.6","49.7","","","","","","","","",""]],"structure":{"data":[{"startDate":"1941/01","endDate":"1950/13","filename":"TYRain_1941-1950_20_pt1-page-084.jpg"},{"startDate":"1951/01","endDate":"1960/13","filename":"TYRain_1951-1960_18_pt1-page-079.jpg"}],"external":[]},"comments":[],"links":{"dataFile":"https://raw.githubusercontent.com/ed-hawkins/rainfall-rescue/v1.1.0/DATA/LOWER-RIVINGTON/LOWER-RIVINGTON-2.csv"},"history":[{"version":"v1.0.0","name":"LOWER-RIVINGTON-2","location":"LOWER-RIVINGTON","changes":["New"]},{"version":"v1.1.0","name":"LOWER-RIVINGTON-2","location":"LOWER-RIVINGTON","changes":[]}]}