{"version":"v1.1.0","name":"SHREWSBURY-NE-MIX-5","location":"SHREWSBURY-NE-MIX","metadata":{"station":"SHREWSBURY MONKSMOOR","gridRef":"SJ502126","stationNo":"RR2027","lon":-2.73853,"lat":52.70876,"elevation":200,"counties":["Shropshire"]},"table":[[1860,1861,1862,1863,1864,1865,1866,1867,1868,1869,1870,1871,1872,1873,1874,1875,1876,1877,1878,1879],["","","","","","","","2.91","2.35","2.76","1.58","1.73","","","","","","","",""],["","","","","","","","1.54","1.9","1.68","1.17","1.37","","","","","","","",""],["","","","","","","","2.48","1.57","1.43","2.12","0.6","","","","","","","",""],["","","","","","","0.95","2.47","1.47","1.08","0.94","2.49","","","","","","","",""],["","","","","","","0.55","2.32","1.62","5.24","0.77","0.85","","","","","","","",""],["","","","","","","3.85","1.43","0.33","0.75","0.6","2.55","","","","","","","",""],["","","","","","","1.46","1.74","0.73","0.84","0.58","3.86","","","","","","","",""],["","","","","","","3.5","0.76","2.36","1.67","1.98","1.29","","","","","","","",""],["","","","","","","5.53","2.8","1.96","5.42","0.85","4.42","","","","","","","",""],["","","","","","","1.33","2.83","1.89","1.93","3.52","3.97","","","","","","","",""],["","","","","","","2.58","0.99","0.83","2.19","2.14","0.83","","","","","","","",""],["","","","","","","1.52","1.83","6.04","2.96","2.06","1.12","","","","","","","",""],["","","","","","","","24.1","23.05","27.95","18.31","25.08","","","","","","","",""]],"structure":{"data":[{"startDate":"1860/01","endDate":"1869/13","filename":"TYRain_1860-1869_03_pt3-page-014.jpg"},{"startDate":"1870/01","endDate":"1879/13","filename":"TYRain_1870-1879_06_pt1-page-062.jpg"}],"external":[]},"comments":["NGR is on Monkmoor Street at about the correct altitude but the location could equally be at Monkmoor, 1 mile NW. I have seen an area 200 to 300 yds NE referred to as Monksmoor but not officially on maps"],"links":{"dataFile":"https://raw.githubusercontent.com/ed-hawkins/rainfall-rescue/v1.1.0/DATA/SHREWSBURY-NE-MIX/SHREWSBURY-NE-MIX-5.csv","imagesFolder":"https://drive.google.com/drive/folders/16K7rVtUFJ9JXjgkk7TYTenuUFfnPWhor"},"history":[{"version":"v1.0.0","location":"SHREWSBURY-NE-MIX","name":"SHREWSBURY-NE-MIX-5","changes":["New"]},{"version":"v1.1.0","location":"SHREWSBURY-NE-MIX","name":"SHREWSBURY-NE-MIX-5","changes":[]},{"version":"v2.0.0","location":"SHREWSBURY-NE-MIX","name":"SHREWSBURY-NE-MIX-5","changes":[]}]}